[
 {
  "id": 26,
  "categoria": "BEVANDE",
  "nome": "ACQUA IN BOTTIGLIA 1/2 LITRO",
  "descrizione": null,
  "prezzo": 2.0,
  "disponibile": true,
  "ordine": 0,
  "created_at": "2026-06-26T17:42:34.519766+00:00"
 },
 {
  "id": 27,
  "categoria": "BEVANDE",
  "nome": "BIBITE IN LATTINA",
  "descrizione": null,
  "prezzo": 3.0,
  "disponibile": true,
  "ordine": 0,
  "created_at": "2026-06-26T17:42:53.797804+00:00"
 },
 {
  "id": 28,
  "categoria": "BEVANDE",
  "nome": "ESTATHE",
  "descrizione": null,
  "prezzo": 3.0,
  "disponibile": true,
  "ordine": 0,
  "created_at": "2026-06-26T17:43:06.050194+00:00"
 },
 {
  "id": 29,
  "categoria": "BIRRA",
  "nome": "BIONDA ALLA SPINA",
  "descrizione": null,
  "prezzo": 5.0,
  "disponibile": true,
  "ordine": 0,
  "created_at": "2026-06-26T17:43:26.09422+00:00"
 },
 {
  "id": 30,
  "categoria": "BIRRA",
  "nome": "ROSSA ALLA SPINA",
  "descrizione": null,
  "prezzo": 5.0,
  "disponibile": true,
  "ordine": 0,
  "created_at": "2026-06-26T17:43:36.700181+00:00"
 },
 {
  "id": 33,
  "categoria": "CAFFE",
  "nome": "CAFFE",
  "descrizione": null,
  "prezzo": 1.0,
  "disponibile": true,
  "ordine": 0,
  "created_at": "2026-06-26T17:44:42.914605+00:00"
 },
 {
  "id": 34,
  "categoria": "CAFFE",
  "nome": "CAFFE CORRETTO",
  "descrizione": null,
  "prezzo": 2.0,
  "disponibile": true,
  "ordine": 0,
  "created_at": "2026-06-26T17:44:54.931542+00:00"
 },
 {
  "id": 50,
  "categoria": "COCKTAIL",
  "nome": "AMERICANO",
  "descrizione": null,
  "prezzo": 5.0,
  "disponibile": true,
  "ordine": 0,
  "created_at": "2026-06-26T17:48:07.960882+00:00"
 },
 {
  "id": 46,
  "categoria": "COCKTAIL",
  "nome": "CUBA LIBRE",
  "descrizione": null,
  "prezzo": 5.0,
  "disponibile": true,
  "ordine": 0,
  "created_at": "2026-06-26T17:47:22.652335+00:00"
 },
 {
  "id": 47,
  "categoria": "COCKTAIL",
  "nome": "CUBANO",
  "descrizione": null,
  "prezzo": 5.0,
  "disponibile": true,
  "ordine": 0,
  "created_at": "2026-06-26T17:47:35.405248+00:00"
 },
 {
  "id": 38,
  "categoria": "COCKTAIL",
  "nome": "GIN LEMON",
  "descrizione": null,
  "prezzo": 5.0,
  "disponibile": true,
  "ordine": 0,
  "created_at": "2026-06-26T17:45:47.400787+00:00"
 },
 {
  "id": 39,
  "categoria": "COCKTAIL",
  "nome": "GIN TONIC",
  "descrizione": null,
  "prezzo": 5.0,
  "disponibile": true,
  "ordine": 0,
  "created_at": "2026-06-26T17:45:55.404588+00:00"
 },
 {
  "id": 44,
  "categoria": "COCKTAIL",
  "nome": "MOJITO",
  "descrizione": null,
  "prezzo": 5.0,
  "disponibile": true,
  "ordine": 0,
  "created_at": "2026-06-26T17:47:04.940456+00:00"
 },
 {
  "id": 45,
  "categoria": "COCKTAIL",
  "nome": "MOSCOW MULE",
  "descrizione": null,
  "prezzo": 5.0,
  "disponibile": true,
  "ordine": 0,
  "created_at": "2026-06-26T17:47:14.803366+00:00"
 },
 {
  "id": 48,
  "categoria": "COCKTAIL",
  "nome": "NEGRONI",
  "descrizione": null,
  "prezzo": 5.0,
  "disponibile": true,
  "ordine": 0,
  "created_at": "2026-06-26T17:47:43.144096+00:00"
 },
 {
  "id": 49,
  "categoria": "COCKTAIL",
  "nome": "NEGRONI SBAGLIATO",
  "descrizione": null,
  "prezzo": 5.0,
  "disponibile": true,
  "ordine": 0,
  "created_at": "2026-06-26T17:47:53.49399+00:00"
 },
 {
  "id": 52,
  "categoria": "COCKTAIL",
  "nome": "RUM E PERA",
  "descrizione": null,
  "prezzo": 3.0,
  "disponibile": true,
  "ordine": 0,
  "created_at": "2026-06-26T17:48:22.046782+00:00"
 },
 {
  "id": 51,
  "categoria": "COCKTAIL",
  "nome": "SPRITZ",
  "descrizione": null,
  "prezzo": 5.0,
  "disponibile": true,
  "ordine": 0,
  "created_at": "2026-06-26T17:48:15.041655+00:00"
 },
 {
  "id": 54,
  "categoria": "COCKTAIL",
  "nome": "TEQUILA BUM BUM",
  "descrizione": null,
  "prezzo": 3.0,
  "disponibile": true,
  "ordine": 0,
  "created_at": "2026-06-26T17:48:46.581393+00:00"
 },
 {
  "id": 53,
  "categoria": "COCKTAIL",
  "nome": "TEQUILA SALE E LIMONE",
  "descrizione": null,
  "prezzo": 3.0,
  "disponibile": true,
  "ordine": 0,
  "created_at": "2026-06-26T17:48:35.878553+00:00"
 },
 {
  "id": 42,
  "categoria": "COCKTAIL",
  "nome": "VODKA E SUCCO DI ARANCIA",
  "descrizione": null,
  "prezzo": 5.0,
  "disponibile": true,
  "ordine": 0,
  "created_at": "2026-06-26T17:46:39.864155+00:00"
 },
 {
  "id": 43,
  "categoria": "COCKTAIL",
  "nome": "VODKA FRAGOLA E LEMON",
  "descrizione": null,
  "prezzo": 5.0,
  "disponibile": true,
  "ordine": 0,
  "created_at": "2026-06-26T17:46:51.824772+00:00"
 },
 {
  "id": 40,
  "categoria": "COCKTAIL",
  "nome": "VODKA LEMON",
  "descrizione": null,
  "prezzo": 5.0,
  "disponibile": true,
  "ordine": 0,
  "created_at": "2026-06-26T17:46:04.7189+00:00"
 },
 {
  "id": 41,
  "categoria": "COCKTAIL",
  "nome": "VODKA TONIC",
  "descrizione": null,
  "prezzo": 5.0,
  "disponibile": true,
  "ordine": 0,
  "created_at": "2026-06-26T17:46:13.680955+00:00"
 },
 {
  "id": 22,
  "categoria": "CONTORNI",
  "nome": "PATATINE FRITTE",
  "descrizione": null,
  "prezzo": 3.0,
  "disponibile": true,
  "ordine": 0,
  "created_at": "2026-06-26T17:41:02.700144+00:00"
 },
 {
  "id": 35,
  "categoria": "DIGESTIVI",
  "nome": "AMARO",
  "descrizione": null,
  "prezzo": 3.0,
  "disponibile": true,
  "ordine": 0,
  "created_at": "2026-06-26T17:45:10.187496+00:00"
 },
 {
  "id": 37,
  "categoria": "DIGESTIVI",
  "nome": "GRAPPA",
  "descrizione": null,
  "prezzo": 3.0,
  "disponibile": true,
  "ordine": 0,
  "created_at": "2026-06-26T17:45:29.301718+00:00"
 },
 {
  "id": 36,
  "categoria": "DIGESTIVI",
  "nome": "LIMONCINO",
  "descrizione": null,
  "prezzo": 3.0,
  "disponibile": true,
  "ordine": 0,
  "created_at": "2026-06-26T17:45:20.805897+00:00"
 },
 {
  "id": 14,
  "categoria": "FOCACCETTE",
  "nome": "FOCACCETTA CON IL CHIODO DI MAIALE",
  "descrizione": null,
  "prezzo": 6.0,
  "disponibile": true,
  "ordine": 0,
  "created_at": "2026-06-26T17:38:14.51725+00:00"
 },
 {
  "id": 11,
  "categoria": "FOCACCETTE",
  "nome": "FOCACCETTA CON IL SALAME",
  "descrizione": null,
  "prezzo": 4.0,
  "disponibile": true,
  "ordine": 0,
  "created_at": "2026-06-26T17:35:50.455035+00:00"
 },
 {
  "id": 13,
  "categoria": "FOCACCETTE",
  "nome": "FOCACCETTA CON LA PANCETTA",
  "descrizione": null,
  "prezzo": 4.0,
  "disponibile": true,
  "ordine": 0,
  "created_at": "2026-06-26T17:37:41.029185+00:00"
 },
 {
  "id": 12,
  "categoria": "FOCACCETTE",
  "nome": "FOCACCETTA CON LO STRACCHINO",
  "descrizione": null,
  "prezzo": 4.0,
  "disponibile": true,
  "ordine": 0,
  "created_at": "2026-06-26T17:36:11.782317+00:00"
 },
 {
  "id": 7,
  "categoria": "PRIMI",
  "nome": "OLIO&FORMAGGIO",
  "descrizione": null,
  "prezzo": 5.0,
  "disponibile": true,
  "ordine": 0,
  "created_at": "2026-06-26T17:33:51.552431+00:00"
 },
 {
  "id": 8,
  "categoria": "PRIMI",
  "nome": "RAVIOLI ALLA PONZANELLESE",
  "descrizione": null,
  "prezzo": 9.0,
  "disponibile": true,
  "ordine": 0,
  "created_at": "2026-06-26T17:34:13.183015+00:00"
 },
 {
  "id": 6,
  "categoria": "PRIMI",
  "nome": "TESTAROI AL PESTO",
  "descrizione": null,
  "prezzo": 5.0,
  "disponibile": true,
  "ordine": 0,
  "created_at": "2026-06-26T17:33:25.45185+00:00"
 },
 {
  "id": 19,
  "categoria": "SECONDI",
  "nome": "ASADO AL PIATTO",
  "descrizione": null,
  "prezzo": 15.0,
  "disponibile": true,
  "ordine": 0,
  "created_at": "2026-06-26T17:40:09.947344+00:00"
 },
 {
  "id": 21,
  "categoria": "SECONDI",
  "nome": "PANINO CON LA PORCHETTA",
  "descrizione": null,
  "prezzo": 5.0,
  "disponibile": true,
  "ordine": 0,
  "created_at": "2026-06-26T17:40:39.154783+00:00"
 },
 {
  "id": 20,
  "categoria": "SECONDI",
  "nome": "PORCHETTA",
  "descrizione": null,
  "prezzo": 9.0,
  "disponibile": true,
  "ordine": 0,
  "created_at": "2026-06-26T17:40:27.567369+00:00"
 },
 {
  "id": 17,
  "categoria": "SGABEI",
  "nome": "SGABEO CON IL CRUDO",
  "descrizione": null,
  "prezzo": 4.0,
  "disponibile": true,
  "ordine": 0,
  "created_at": "2026-06-26T17:39:17.006337+00:00"
 },
 {
  "id": 10,
  "categoria": "SGABEI",
  "nome": "SGABEO CON IL SALAME",
  "descrizione": null,
  "prezzo": 4.0,
  "disponibile": true,
  "ordine": 0,
  "created_at": "2026-06-26T17:35:11.187255+00:00"
 },
 {
  "id": 18,
  "categoria": "SGABEI",
  "nome": "SGABEO CON LA NUTELLA",
  "descrizione": null,
  "prezzo": 4.0,
  "disponibile": true,
  "ordine": 0,
  "created_at": "2026-06-26T17:39:29.67272+00:00"
 },
 {
  "id": 16,
  "categoria": "SGABEI",
  "nome": "SGABEO CON LA PANCETTA",
  "descrizione": null,
  "prezzo": 4.0,
  "disponibile": true,
  "ordine": 0,
  "created_at": "2026-06-26T17:39:05.289938+00:00"
 },
 {
  "id": 15,
  "categoria": "SGABEI",
  "nome": "SGABEO CON LO STRACCHINO",
  "descrizione": null,
  "prezzo": 4.0,
  "disponibile": true,
  "ordine": 0,
  "created_at": "2026-06-26T17:38:49.759012+00:00"
 },
 {
  "id": 9,
  "categoria": "SGABEI",
  "nome": "SGABEO VUOTO",
  "descrizione": null,
  "prezzo": 2.0,
  "disponibile": true,
  "ordine": 0,
  "created_at": "2026-06-26T17:34:36.505791+00:00"
 },
 {
  "id": 25,
  "categoria": "TORTE",
  "nome": "3 FETTE DI TORTA DOLCE",
  "descrizione": null,
  "prezzo": 4.0,
  "disponibile": true,
  "ordine": 0,
  "created_at": "2026-06-26T17:41:48.495285+00:00"
 },
 {
  "id": 24,
  "categoria": "TORTE",
  "nome": "3 FETTE DI TORTA SALATA",
  "descrizione": null,
  "prezzo": 4.0,
  "disponibile": true,
  "ordine": 0,
  "created_at": "2026-06-26T17:41:38.909921+00:00"
 },
 {
  "id": 23,
  "categoria": "VEGANO",
  "nome": "PIATTO VEGANO",
  "descrizione": null,
  "prezzo": 5.0,
  "disponibile": true,
  "ordine": 0,
  "created_at": "2026-06-26T17:41:16.872945+00:00"
 },
 {
  "id": 32,
  "categoria": "VINO",
  "nome": "BICCHIERE",
  "descrizione": null,
  "prezzo": 2.0,
  "disponibile": true,
  "ordine": 0,
  "created_at": "2026-06-26T17:44:24.219659+00:00"
 },
 {
  "id": 31,
  "categoria": "VINO",
  "nome": "BOTTIGLIA",
  "descrizione": "3 SESTERZI DI CAUZIONE PER LA BOTTIGLIA",
  "prezzo": 7.0,
  "disponibile": true,
  "ordine": 0,
  "created_at": "2026-06-26T17:44:14.703393+00:00"
 }
]